LICENSE
README.md
pyproject.toml
setup.py
definitely_typed/__init__.py
definitely_typed/asyncily.py
definitely_typed/definitely.py
definitely_typed/reversely.py
definitely_typed.egg-info/PKG-INFO
definitely_typed.egg-info/SOURCES.txt
definitely_typed.egg-info/dependency_links.txt
definitely_typed.egg-info/requires.txt
definitely_typed.egg-info/top_level.txt