Metadata-Version: 2.1
Name: definitely-typed
Version: 0.2
Summary: Definitely typed. Type any object to any type as you wish.
Author-email: AWeirdDev <aweirdscratcher@gmail.com>
License: MIT License
Project-URL: Source, https://github.com/AWeirdDev/definitely
Project-URL: Bug Tracker, https://github.com/AWeirdDev/definitely/issues
Keywords: typing,definitely,type-hints
Classifier: Programming Language :: Python :: 3
Classifier: License :: OSI Approved :: MIT License
Classifier: Operating System :: OS Independent
Requires-Python: >=3.9
License-File: LICENSE
Requires-Dist: typing-extensions
